{
  "config": {
    "step": {
      "user": {
        "title": "getAir SmartControl Konfiguration",
        "description": "Geben Sie Ihre getAir Anmeldedaten ein",
        "data": {
          "auth_url": "Authentifizierungs-URL",
          "api_url": "API-URL",
          "client_id": "Client-ID",
          "username": "Benutzername",
          "password": "Passwort"
        }
      },
      "select_device": {
        "title": "Gerät auswählen",
        "description": "Es wurden {device_count} Geräte gefunden. Bitte wählen Sie eines aus:",
        "data": {
          "device_id": "Gerät"
        }
      }
    },
    "error": {
      "cannot_connect": "Verbindung fehlgeschlagen: {error_details}",
      "invalid_credentials": "Ungültige Anmeldedaten",
      "no_devices": "Keine Geräte gefunden"
    },
    "abort": {
      "already_configured": "Gerät bereits konfiguriert"
    }
  },
  "options": {
    "step": {
      "init": {
        "title": "getAir SmartControl Optionen",
        "description": "Passen Sie die Integration an",
        "data": {
          "polling_interval": "Abfrage-Intervall (Sekunden)",
          "enable_zone_1": "Zone 1 aktivieren",
          "enable_zone_2": "Zone 2 aktivieren",
          "enable_zone_3": "Zone 3 aktivieren"
        }
      }
    }
  },
  "entity": {
    "sensor": {
      "system_air_quality": {
        "name": "Luftqualität (IAQ)"
      },
      "system_air_pressure": {
        "name": "Luftdruck"
      },
      "system_humidity": {
        "name": "Luftfeuchtigkeit"
      },
      "system_temperature": {
        "name": "Temperatur"
      },
      "system_runtime": {
        "name": "Gesamtlaufzeit"
      },
      "system_boot_time": {
        "name": "Boot-Zeit"
      },
      "system_iaq_accuracy": {
        "name": "IAQ-Genauigkeit"
      },
      "system_num_zones": {
        "name": "Anzahl Zonen"
      },
      "system_modelock": {
        "name": "Modus-Sperre"
      },
      "last_update": {
        "name": "Letzte Aktualisierung"
      },
      "connection_status": {
        "name": "Verbindungsstatus"
      },
      "system_type": {
        "name": "System-Typ"
      },
      "system_version": {
        "name": "Systemversion"
      },
      "system_fw_app_version": {
        "name": "Firmware-Version"
      },
      "system_notification": {
        "name": "Benachrichtigung"
      },
      "system_notification_time": {
        "name": "Benachrichtigungszeit"
      },
      "zone_temperature": {
        "name": "Temperatur (innen)"
      },
      "zone_humidity": {
        "name": "Luftfeuchtigkeit (innen)"
      },
      "zone_outdoor_temperature": {
        "name": "Temperatur (außen)"
      },
      "zone_outdoor_humidity": {
        "name": "Luftfeuchtigkeit (außen)"
      },
      "zone_runtime": {
        "name": "Laufzeit"
      },
      "zone_filter_runtime": {
        "name": "Filter-Laufzeit"
      },
      "zone_target_temperature": {
        "name": "Zieltemperatur"
      },
      "zone_target_humidity": {
        "name": "Ziel-Luftfeuchtigkeitsbereich"
      },
      "zone_time_profile": {
        "name": "Aktives Zeitprofil"
      },
      "time_profile_1_name": {
        "name": "Zeitprofil 1 Name"
      },
      "time_profile_2_name": {
        "name": "Zeitprofil 2 Name"
      },
      "time_profile_3_name": {
        "name": "Zeitprofil 3 Name"
      },
      "time_profile_4_name": {
        "name": "Zeitprofil 4 Name"
      },
      "time_profile_5_name": {
        "name": "Zeitprofil 5 Name"
      },
      "time_profile_6_name": {
        "name": "Zeitprofil 6 Name"
      },
      "time_profile_7_name": {
        "name": "Zeitprofil 7 Name"
      },
      "time_profile_8_name": {
        "name": "Zeitprofil 8 Name"
      },
      "time_profile_9_name": {
        "name": "Zeitprofil 9 Name"
      },
      "time_profile_10_name": {
        "name": "Zeitprofil 10 Name"
      }
    },
    "binary_sensor": {
      "system_modelock": {
        "name": "Modus-Sperre"
      },
      "system_supports_auto_update": {
        "name": "Unterstützt Auto-Update"
      },
      "system_auto_update_enabled": {
        "name": "Auto-Update aktiviert"
      }
    },
    "select": {
      "zone_mode": {
        "name": "Betriebsmodus",
        "state": {
          "ventilate": "Normales Lüften",
          "ventilate_hr": "Lüften mit WRG",
          "ventilate_inv": "Inverses Lüften",
          "night": "Nachtmodus",
          "auto": "Automatik",
          "rush": "Stoßlüften",
          "rush_hr": "Stoßlüften mit WRG",
          "rush_inv": "Inverses Stoßlüften"
        }
      },
      "zone_target_humidity_control": {
        "name": "Ziel-Luftfeuchtigkeit"
      },
      "zone_time_profile_control": {
        "name": "Zeitprofil"
      }
    },
    "fan": {
      "zone_1": {
        "name": "Lüfter"
      },
      "zone_2": {
        "name": "Lüfter"
      },
      "zone_3": {
        "name": "Lüfter"
      }
    },
    "number": {
      "zone_target_temperature_control": {
        "name": "Zieltemperatur"
      },
      "zone_filter_runtime_control": {
        "name": "Filter-Laufzeit zurücksetzen"
      },
      "zone_time_profile_control": {
        "name": "Zeitprofil"
      },
      "zone_mode_deadline_control": {
        "name": "Modus-Deadline (Minuten)"
      }
    },
    "switch": {
      "zone_auto_mode_voc_switch": {
        "name": "VOC Auto-Modus"
      },
      "zone_auto_mode_silent_switch": {
        "name": "Silent-Modus"
      }
    },
    "text": {
      "zone_name": {
        "name": "Zonenname"
      }
    },
    "button": {
      "zone_reset_filter_runtime": {
        "name": "Filter-Laufzeit zurücksetzen"
      },
      "zone_reset_mode_deadline": {
        "name": "Modus-Deadline zurücksetzen"
      }
    }
  },
  "entity_component": {
    "_": {
      "state": {
        "ventilate": "Normales Lüften",
        "ventilate_hr": "Lüften mit WRG",
        "ventilate_inv": "Inverses Lüften",
        "night": "Nachtmodus",
        "auto": "Automatik",
        "rush": "Stoßlüften",
        "rush_hr": "Stoßlüften mit WRG",
        "rush_inv": "Inverses Stoßlüften"
      }
    }
  }
}
